Bluetooth/__init__.py
Bluetooth/bth_1208LS.py
Bluetooth/mccBluetooth.py
Ethernet/E_1608.py
Ethernet/E_DIO24.py
Ethernet/E_TC.py
Ethernet/E_TC32.py
Ethernet/__init__.py
Ethernet/mccEthernet.py
mcc_linux_drivers-0.1.1.dist-info/METADATA
mcc_linux_drivers-0.1.1.dist-info/WHEEL
mcc_linux_drivers-0.1.1.dist-info/top_level.txt
mcc_linux_drivers-0.1.1.dist-info/RECORD
