Metadata-Version: 2.1
Name: mcc_linux_drivers
Version: 0.1.1
Summary: Linux Drivers for MCC
Home-page: https://github.com/wjasper/Linux_Drivers
Author: W. Jasper
Author-email: wjasper@ncsu.edu
Requires-Python: >=3.6
